MANIFEST.in
setup.py
lesioneditor/Data.py
lesioneditor/Form_widget.py
lesioneditor/Lesion.py
lesioneditor/Lession_editor.py
lesioneditor/Lession_editor_slim.py
lesioneditor/Lession_editor_slim_test.py
lesioneditor/My_table_model.py
lesioneditor/My_table_model_old.py
lesioneditor/TumorVisualiser.py
lesioneditor/Viewer_3D.py
lesioneditor/__init__.py
lesioneditor/area_hist_widget.py
lesioneditor/area_hist_widget_GUI.py
lesioneditor/bootstrap.py
lesioneditor/computational_core.py
lesioneditor/config.ini
lesioneditor/data_view_widget.py
lesioneditor/hist_widget.py
lesioneditor/hist_widget_GUI.py
lesioneditor/hist_widget_old.py
lesioneditor/lesion_editor_GUI_hand.py
lesioneditor/lession_editor_GUI.py
lesioneditor/lession_editor_GUI_slim.py
lesioneditor/lession_editor_GUI_slim2.py
lesioneditor/mrf_gmm_test.py
lesioneditor/objects_widget.py
lesioneditor/objects_widget_GUI.py
lesioneditor/old_Computational_core.py
lesioneditor/py3DSeedEditor.py
lesioneditor/qrangeslider.py
lesioneditor/seed_editor_qt.py
lesioneditor/simple_viewer.py
lesioneditor/tools.py
lesioneditor/view_widget_test.py
lesioneditor.egg-info/PKG-INFO
lesioneditor.egg-info/SOURCES.txt
lesioneditor.egg-info/dependency_links.txt
lesioneditor.egg-info/pbr.json
lesioneditor.egg-info/top_level.txt
lesioneditor/icons/Blue tag.png
lesioneditor/icons/Brush.png
lesioneditor/icons/Eye.png
lesioneditor/icons/Stock graph.png